README.rst
setup.cfg
setup.py
cizsle/__init__.py
cizsle/_metadata.py
cizsle.egg-info/PKG-INFO
cizsle.egg-info/SOURCES.txt
cizsle.egg-info/dependency_links.txt
cizsle.egg-info/entry_points.txt
cizsle.egg-info/requires.txt
cizsle.egg-info/top_level.txt
cizsle/client/__init__.py
cizsle/client/__main__.py
cizsle/server/__init__.py
cizsle/server/__main__.py