Metadata-Version: 2.1
Name: cizsle
Version: 0.0a7
Summary: Cisco ZTP Server LE
Home-page: https://github.com/CiscoDevNet/cizsle
Author: Cisco and Contributors
Author-email: cizsle@cisco.com
License: UNKNOWN
Download-URL: https://pypi.python.org/pypi/cizsle
Keywords: cisco ztp ios-xe catalyst
Platform: UNKNOWN
Classifier: Development Status :: 3 - Alpha
Classifier: Programming Language :: Python :: 3
Classifier: Programming Language :: Python :: 3 :: Only
Classifier: Programming Language :: Python :: 3.6
Classifier: Natural Language :: English
Classifier: Intended Audience :: System Administrators
Classifier: Intended Audience :: Telecommunications Industry
Classifier: Topic :: System :: Networking
Classifier: Topic :: System :: Installation/Setup
Classifier: Topic :: System :: Software Distribution
Provides-Extra: server
